clishelf-0.3.2.dist-info/METADATA
clishelf-0.3.2.dist-info/WHEEL
clishelf-0.3.2.dist-info/entry_points.txt
clishelf-0.3.2.dist-info/licenses/LICENSE
clishelf/__about__.py
clishelf/__init__.py
clishelf/__main__.py
clishelf/assets/emoji.json
clishelf/bump/__init__.py
clishelf/bump/bump.py
clishelf/bump/bump_cli.py
clishelf/bump/cli.py
clishelf/bump/conf.py
clishelf/bump/incremeters.py
clishelf/bump/utils.py
clishelf/bump/vcs.py
clishelf/bump/version_part.py
clishelf/cli.py
clishelf/emoji.py
clishelf/errors.py
clishelf/git.py
clishelf/settings.py
clishelf/utils.py
clishelf-0.3.2.dist-info/RECORD
