Metadata-Version: 2.1
Name: clishelf
Version: 0.3.2
Summary: A CLI tools and hooks on my shelf
Keywords: utility,cli
Author-Email: korawica <korawich.anu@gmail.com>
Classifier: Topic :: Utilities
Classifier: Natural Language :: English
Classifier: Development Status :: 4 - Beta
Classifier: Operating System :: OS Independent
Classifier: License :: OSI Approved :: MIT License
Classifier: Programming Language :: Python
Classifier: Programming Language :: Python :: 3 :: Only
Classifier: Programming Language :: Python :: 3.10
Classifier: Programming Language :: Python :: 3.11
Classifier: Programming Language :: Python :: 3.12
Classifier: Programming Language :: Python :: 3.13
Classifier: Programming Language :: Python :: 3.14
Project-URL: Homepage, https://github.com/korawica/clishelf/
Project-URL: Source Code, https://github.com/korawica/clishelf/
Requires-Python: >=3.10
Requires-Dist: click>=8.1.8
Requires-Dist: PyYAML>=6.0.3
Requires-Dist: pip; python_version <= "3.10"
Requires-Dist: typing_extensions; python_version <= "3.10"
Provides-Extra: test
Requires-Dist: clishelf[all]; extra == "test"
Requires-Dist: pytest; extra == "test"
Requires-Dist: requests; extra == "test"
Requires-Dist: tomli-w; extra == "test"
Provides-Extra: all
Requires-Dist: pre-commit>=4.0.0; extra == "all"
Provides-Extra: latest
Requires-Dist: click==8.3.0; extra == "latest"
Requires-Dist: PyYAML==6.0.3; extra == "latest"
